Metadata-Version: 2.1
Name: peewee-migrate-dev
Version: 0.0.1a0
Summary: Simple migration engine for Peewee
Home-page: https://github.com/klen/peewee_migrate
Author: Kirill Klenov
Author-email: horneds@gmail.com
License: BSD
Keywords: django,flask,sqlalchemy,testing,mock,stub,mongoengine,data
Platform: Any
Classifier: Development Status :: 4 - Beta
Classifier: Intended Audience :: Developers
Classifier: License :: OSI Approved :: BSD License
Classifier: Natural Language :: English
Classifier: Natural Language :: Russian
Classifier: Operating System :: OS Independent
Classifier: Programming Language :: Python :: 2
Classifier: Programming Language :: Python :: 3
Classifier: Programming Language :: Python
Classifier: Topic :: Software Development :: Libraries :: Python Modules
Classifier: Topic :: Software Development :: Testing
Classifier: Topic :: Utilities
Requires-Dist: cached-property (>=1.4.2)
Requires-Dist: click (>=6.7)
Requires-Dist: mock (>=2.0.0)
Requires-Dist: peewee (>=3.3.3)
